{
    "nbody": 3,
    "n_int": 49152,
    "mass": [
        1.0,
        1.0,
        1.0
    ],
    "nloop": 1,
    "Action": 78.28600677328087,
    "Grad_Action": 7.236167473341976e-14,
    "Newton_Error": 2.0020034307110748e-14,
    "Min_Distance": 0.014621035055251854,
    "Max_PathLength": 3.9315742084213943,
    "Hash": [
        78.28600677328087,
        35.1773892294517,
        54.88285732143294,
        121.8877634880686,
        360.9010190145117
    ],
    "xinf": -0.058183556770123365,
    "xsup": 0.08085975046605344,
    "yinf": -0.06952165361808835,
    "ysup": 0.06952165361808846,
    "loopnb": [
        3
    ],
    "Targets": [
        [
            0,
            1,
            2
        ]
    ],
    "SpaceRotsUn": [
        [
            [
                [
                    1.0,
                    0.0
                ],
                [
                    0.0,
                    1.0
                ]
            ],
            [
                [
                    1.0,
                    0.0
                ],
                [
                    0.0,
                    1.0
                ]
            ],
            [
                [
                    1.0,
                    0.0
                ],
                [
                    0.0,
                    1.0
                ]
            ]
        ]
    ],
    "TimeRevsUn": [
        [
            1,
            1,
            1
        ]
    ],
    "TimeShiftNumUn": [
        [
            0,
            1,
            2
        ]
    ],
    "TimeShiftDenUn": [
        [
            1,
            3,
            3
        ]
    ],
    "RequiresLoopDispUn": [
        [
            true,
            false,
            false
        ]
    ]
}