{
    "nbody": 10,
    "n_Fourier": 50,
    "n_int": 100,
    "mass": [
        1.0,
        1.0,
        1.0,
        1.0,
        1.0,
        1.0,
        1.0,
        1.0,
        1.0,
        1.0
    ],
    "nloop": 10,
    "Action": 41.53934002368433,
    "Grad_Action": 3.246076485725174e-10,
    "Newton_Error": 2.2953189344666283e-12,
    "Min_Distance": 0.27547981609031547,
    "Max_PathLength": 3.7299880955314744,
    "Hash": [
        124.61802007096128,
        97.80075731281828,
        113.95474732216877,
        137.56271898857528,
        172.64692871625263
    ],
    "xinf": -0.5935770003330458,
    "xsup": 0.5935770003330458,
    "yinf": -0.5935770003330458,
    "ysup": 0.5935770003330458,
    "loopnb": [
        1,
        1,
        1,
        1,
        1,
        1,
        1,
        1,
        1,
        1
    ],
    "Targets": [
        [
            0
        ],
        [
            1
        ],
        [
            2
        ],
        [
            3
        ],
        [
            4
        ],
        [
            5
        ],
        [
            6
        ],
        [
            7
        ],
        [
            8
        ],
        [
            9
        ]
    ],
    "SpaceRotsUn": [
        [
            [
                [
                    1.0,
                    0.0
                ],
                [
                    0.0,
                    1.0
                ]
            ]
        ],
        [
            [
                [
                    1.0,
                    0.0
                ],
                [
                    0.0,
                    1.0
                ]
            ]
        ],
        [
            [
                [
                    1.0,
                    0.0
                ],
                [
                    0.0,
                    1.0
                ]
            ]
        ],
        [
            [
                [
                    1.0,
                    0.0
                ],
                [
                    0.0,
                    1.0
                ]
            ]
        ],
        [
            [
                [
                    1.0,
                    0.0
                ],
                [
                    0.0,
                    1.0
                ]
            ]
        ],
        [
            [
                [
                    1.0,
                    0.0
                ],
                [
                    0.0,
                    1.0
                ]
            ]
        ],
        [
            [
                [
                    1.0,
                    0.0
                ],
                [
                    0.0,
                    1.0
                ]
            ]
        ],
        [
            [
                [
                    1.0,
                    0.0
                ],
                [
                    0.0,
                    1.0
                ]
            ]
        ],
        [
            [
                [
                    1.0,
                    0.0
                ],
                [
                    0.0,
                    1.0
                ]
            ]
        ],
        [
            [
                [
                    1.0,
                    0.0
                ],
                [
                    0.0,
                    1.0
                ]
            ]
        ]
    ],
    "TimeRevsUn": [
        [
            1
        ],
        [
            1
        ],
        [
            1
        ],
        [
            1
        ],
        [
            1
        ],
        [
            1
        ],
        [
            1
        ],
        [
            1
        ],
        [
            1
        ],
        [
            1
        ]
    ],
    "TimeShiftNumUn": [
        [
            0
        ],
        [
            0
        ],
        [
            0
        ],
        [
            0
        ],
        [
            0
        ],
        [
            0
        ],
        [
            0
        ],
        [
            0
        ],
        [
            0
        ],
        [
            0
        ]
    ],
    "TimeShiftDenUn": [
        [
            1
        ],
        [
            1
        ],
        [
            1
        ],
        [
            1
        ],
        [
            1
        ],
        [
            1
        ],
        [
            1
        ],
        [
            1
        ],
        [
            1
        ],
        [
            1
        ]
    ],
    "RequiresLoopDispUn": [
        [
            true
        ],
        [
            true
        ],
        [
            true
        ],
        [
            true
        ],
        [
            true
        ],
        [
            true
        ],
        [
            true
        ],
        [
            true
        ],
        [
            true
        ],
        [
            true
        ]
    ]
}